<PAMDataset>
  <PAMRasterBand band="1">
    <Histograms>
      <HistItem>
        <HistMin>6.375970340099999</HistMin>
        <HistMax>15.0043098599</HistMax>
        <BucketCount>1000</BucketCount>
        <IncludeOutOfRange>0</IncludeOutOfRange>
        <Approximate>1</Approximate>
        <HistCounts>13|8|3|3|4|4|3|4|3|4|3|9|12|11|11|9|9|9|7|9|9|9|9|7|9|9|9|9|7|9|9|9|9|8|8|8|5|5|5|7|9|4|4|4|3|4|3|4|4|3|3|4|4|4|2|4|4|3|4|2|4|3|4|2|4|4|3|4|2|4|3|4|2|4|4|3|4|2|4|3|4|2|4|4|4|2|4|4|3|4|3|4|3|4|3|3|4|4|4|2|4|4|3|3|4|4|3|3|5|33|22|8|7|6|7|7|6|6|7|9|7|7|8|8|8|6|8|7|8|7|6|7|7|8|6|7|7|7|7|6|8|6|8|6|7|7|7|6|7|7|8|6|7|6|8|7|9|12|13|12|13|12|11|13|12|12|11|13|10|9|8|9|10|10|12|12|12|11|7|7|8|7|7|7|7|8|6|7|7|8|8|6|6|8|8|7|6|7|8|7|7|6|8|8|7|7|6|8|7|7|7|7|8|7|7|7|8|40|28|12|14|11|9|12|11|11|10|8|11|11|10|10|12|13|14|13|13|10|12|11|12|11|12|11|11|12|12|12|10|12|12|13|10|9|11|12|11|10|10|11|11|11|10|9|12|12|11|9|10|12|11|10|10|11|11|11|11|10|10|11|11|10|11|10|11|10|12|11|10|11|12|12|10|11|11|12|12|12|9|11|13|12|13|11|1237|34|34|28|33|31|32|31|32|31|30|36|30|35|62|65|52|50|47|43|34|37|41|45|42|45|40|45|42|45|42|47|52|34|33|33|38|34|33|36|33|38|34|35|38|33|38|35|35|39|39|38|39|38|42|37|40|38|47|43|47|45|53|54|67|31|35|33|33|28|34|44|45|44|42|43|47|42|48|43|44|46|52|54|44|44|45|44|44|45|42|46|43|50|56|61|59|37|36|36|38|32|40|34|37|40|35|40|37|43|37|38|43|40|38|41|36|32|40|37|38|33|43|55|62|82|63|41|47|43|50|47|46|41|40|44|44|44|36|39|36|41|39|31|37|34|39|40|42|47|43|51|65|30|25|24|24|29|21|30|27|27|32|27|47|40|46|43|39|53|46|42|44|44|46|57|52|51|69|33|34|30|29|33|29|31|30|26|32|32|38|35|35|33|31|29|35|39|43|31|34|39|41|45|55|54|47|37|31|41|31|36|39|34|30|34|30|32|33|40|34|36|33|34|35|39|36|36|44|47|49|51|19|28|28|21|27|27|26|25|26|27|23|29|27|59|48|36|38|38|35|36|37|31|35|32|38|31|35|42|40|43|51|44|32|23|27|24|25|22|30|25|24|26|22|24|21|27|23|22|28|48|58|44|37|34|35|35|34|38|34|38|47|43|47|43|27|26|23|23|25|19|24|23|23|26|19|27|24|22|24|25|25|19|21|20|33|62|51|41|38|34|37|39|38|48|57|36|19|25|23|24|21|25|23|19|23|24|22|25|20|26|21|23|24|24|19|23|20|21|24|22|26|49|44|48|39|37|42|40|63|25|20|20|22|22|21|22|22|21|25|24|20|20|22|22|23|21|23|20|18|24|18|26|20|19|22|22|26|23|24|24|25|27|27|33|30|75|29|22|28|33|37|22|23|23|20|24|29|20|23|20|20|18|23|21|21|25|24|24|26|22|18|22|25|20|25|23|26|25|27|34|25|34|40|15|16|13|16|13|14|37|39|46|17|26|24|25|25|22|21|21|21|21|23|20|22|24|23|17|24|22|22|24|29|25|30|35|31|43|12|18|13|14|19|15|14|13|13|14|14|34|60|30|22|25|32|26|25|27|21|29|33|33|30|40|35|39|16|18|14|14|14|15|14|14|11|15|17|15|17|15|15|11|14|12|13|28|56|31|51|33|27|41|50|47|17|18|16|18|16|17|16|14|15|14|16|17|15|20|14|13|19|19|11|16|12|12|17|19|20|26|60|59|29|25|29|26|21|14|16|16|15|15|16|14|21|17|18|16|19|17|18|17|14|23|25|23|20|21|33|39|8|4|3|3|7|6|4|10|41|25|33|15|18|18|14|15|15|15|15|14|16|14|14|12|15|15|12|15|16|34|24|18|20|56|41|5|5|2|4|1|5|4|4|8|4|4|8|5|7|5|6|5|4|4|4|5|29|71|38|15|16|15|14|19|18|21|19|58|62|46|8|7|8|9|6|7|3|4|3|3|3|5|3|3|3|3|4|6|7|5|8|7|4|3|7|9|8|6|6|9|9|6|29|54|147|28|20|21|18|16|9|11|10|1345</HistCounts>
      </HistItem>
    </Histograms>
    <Metadata>
      <MDI key="STATISTICS_MAXIMUM">15</MDI>
      <MDI key="STATISTICS_MEAN">11.184661089497</MDI>
      <MDI key="STATISTICS_MINIMUM">6.3802802</MDI>
      <MDI key="STATISTICS_STDDEV">2.0802060106251</MDI>
    </Metadata>
  </PAMRasterBand>
</PAMDataset>
